webhelpers2_grid/__init__.py
webhelpers2_grid/stylesheets/grid.css
webhelpers2_grid-0.9.dist-info/METADATA
webhelpers2_grid-0.9.dist-info/RECORD
webhelpers2_grid-0.9.dist-info/WHEEL
webhelpers2_grid-0.9.dist-info/top_level.txt
webhelpers2_grid-0.9.dist-info/zip-safe
