Metadata-Version: 2.1
Name: webhelpers2-grid
Version: 0.9
Summary: HTML Grid renderer that helps generating HTML tables (or other structures)
Home-page: UNKNOWN
Author: Marcin Lulek
Author-email: info@webreactor.eu
License: BSD
Platform: UNKNOWN
Classifier: Intended Audience :: Developers
Classifier: License :: OSI Approved :: BSD License
Classifier: Programming Language :: Python
Classifier: Programming Language :: Python :: 2
Classifier: Programming Language :: Python :: 3
Classifier: Development Status :: 4 - Beta
Classifier: Framework :: Pyramid
Classifier: Framework :: Django
Classifier: Framework :: Flask
Classifier: Framework :: Pylons
Classifier: Topic :: Internet :: WWW/HTTP
Provides-Extra: lint
Provides-Extra: dev
Requires-Dist: webhelpers2
Provides-Extra: dev
Requires-Dist: coverage; extra == 'dev'
Requires-Dist: pytest; extra == 'dev'
Requires-Dist: tox; extra == 'dev'
Requires-Dist: mock; extra == 'dev'
Requires-Dist: jinja2; extra == 'dev'
Provides-Extra: lint
Requires-Dist: black; extra == 'lint'
